Simplesquare/__init__.py
Simplesquare/__main__.py
Simplesquare-0.0.1.dist-info/LICENSE.txt
Simplesquare-0.0.1.dist-info/METADATA
Simplesquare-0.0.1.dist-info/WHEEL
Simplesquare-0.0.1.dist-info/entry_points.txt
Simplesquare-0.0.1.dist-info/top_level.txt
Simplesquare-0.0.1.dist-info/RECORD
