Metadata-Version: 2.1
Name: Simplesquare
Version: 0.0.1
Summary: It square the number
Home-page: https://github.com/DPrakashMewari/Mathsimple
Author: Chandra Prakash Mewari
Author-email: Prakash.mewari@yahoo.com
License: MIT
Platform: UNKNOWN
Classifier: License :: OSI Approved :: MIT License
Classifier: Programming Language :: Python :: 3.6
Classifier: Programming Language :: Python :: 3.7
Classifier: Programming Language :: Python :: 3.8
